[{"content":"Unser Verein Der Verein digital.austria wurde 2017 gegründet. Die beiden Gründer Anton Kalcik und Daniel Wagner hatten ihre ersten Erfahrungen beim CoderDojo Linz gesammelt. Rasch war allerdins der Entschluss das CoderDojo in Wien starten zu wollen gefasst. Das erste CoderDojo Wien fand am 28. April 2017 statt.\nErstes CoderDojo WienGastgeber Firma VERBUND\nSeither ist viel geschehen, maches hat sich verändert und weiterentwickelt. Gleich gelieben ist der Glaube an die Ursprungsidee von CoderDojo\nUnsere Mission CoderDojo bietet Kindern im Alter von 8 bis 17 Jahren eine kostenlose, sichere und unterhaltsame Umgebung, um das Programmieren zu lernen. CoderDojo gibt Kindern die Möglichkeit, die Technologie zu entdecken und zu verstehen, die unsere Welt prägt.\nIn regelmäßigen Treffen wird gelernt wie man Code schreibt, Webseiten entwickelt oder Apps und Spiele programmiert.\nTeilnehmen können Kinder und Jugendliche im Alter von 8 bis 17 Jahren. Es sind keine Vorkenntnisse notwendig und die Teilnahme ist kostenfrei.\nKinder unter 13 Jahren müssen von einem Erwachsenen begleitet werden.\nZur Zeit gibt es jeden Freitag virtuelle CoderDojos von unseren Freunden des CoderDojo Linz an denen du vie Zoom teilnehmen kannst.\nEs gibt in Wien jede zweite Woche und in Tulln einmal in Monat ein persönliches Treffen zum gemeinsamen Programmieren. Für diese ist eine Anmeldung erforderlich.\nNeben unseren regelmäßigen Aktivitäten engagieren wir uns beispielsweise auch bei Coding-Workshops in Schulen oder unterstützen mit unserem Know-How bei anderen Veranstaltungen.\nUnser Board Daniel Wagner Obmann\nKarl Sträßler Obmann Stellvertreter\nKatharina Unlayao Kassierin\nRigerta Demiri Schriftführerin\n","permalink":"https://digital-austria.at/page/about/","summary":"Unser Verein Der Verein digital.austria wurde 2017 gegründet. Die beiden Gründer Anton Kalcik und Daniel Wagner hatten ihre ersten Erfahrungen beim CoderDojo Linz gesammelt. Rasch war allerdins der Entschluss das CoderDojo in Wien starten zu wollen gefasst. Das erste CoderDojo Wien fand am 28. April 2017 statt.\nErstes CoderDojo WienGastgeber Firma VERBUND\nSeither ist viel geschehen, maches hat sich verändert und weiterentwickelt. Gleich gelieben ist der Glaube an die Ursprungsidee von CoderDojo","title":"Über uns"},{"content":"Informationen für Eltern Was ist ein CoderDojo? In der weltweiten CoderDojo Gemeinschaft bieten Freiwillige Programmierclubs für Kinder und Jugendliche an. Dort wird spielerisch Technologie entdeckt und gelernt wie man Code schreibt, Webseiten entwickelt, Apps und Spiele programmiert und vieles mehr. Technologieinteressierte Kinder treffen Gleichgesinnte und können sich über ihre Projekte austauschen.\nGemeinsames Entdecken, Teamarbeit, Mentoring sowie selbstorganisiertes Lernen und Experimentieren stehen im CoderDojo im Vordergrund. Offenheit, gegenseitiges Helfen und das Weitergeben von erworbenem Wissen sind wichtige Grundprinzipien. An oberster Stelle steht aber die Förderung von Kreativität und Spaß an Technologie. Softwareentwicklung in einer Gemeinschaft soll Spaß machen, cool sein und den Kindern neue Perspektiven in einer Welt eröffnen, die immer mehr von Technologie, Computern und Software geprägt ist.\nInternationale CoderDojo-Gemeinschaft (Englisch) Was ist ein Dōjō (道場)? Ist Programmieren wichtig für mein Kind? In der heutigen Welt sind wir von Technologie umgeben, die durch Software gesteuert wird. Programmieren ist daher eine wichtige Fähigkeit. Sie wird Ihren Kindern in der Ausbildung und manchmal auch im Alltagsleben helfen.\nIm Gegensatz zu Mathematik oder Physik ist Programmieren noch kein fester Bestandteil im Schulalltag. Bei den CoderDojos lernen Kinder spielerisch Technologie und Programmieren kennen. Nebenbei werden dabei logisches Denken, Teamarbeit, Englisch u.v.m. gefördert.\nNeben dem Erwerben zusätzlicher Fähigkeiten sollen CoderDojos auch die Perspektive der Kinder und Jugendlichen in Sachen Berufswahl erweitern. Gute Technikerinnen und Techniker sind sehr gefragt. In CoderDojos können Ihre Kinder herausfinden, ob ihnen ein technischer Beruf im Bereich Softwareentwicklung Spaß machen könnte.\nWas sind CoderDojos nicht? CoderDojos sind kein Schulunterricht, keine Nachhilfestunden und keine Treffen zum Computerspielen.\nComputerspiele sind ein wichtiges Element beim CoderDojo. Statt diese aber nur zu konsumieren, erstellen oder erweitern Kinder und Jugendliche sie im CoderDojo selbst.\nWelche Regeln gibt es? Bei den Projekten sind kaum Grenzen gesetzt. Spiele, Elektronik, Apps oder Webseiten, alles ist möglich. Die Mentoren achten darauf, dass die Projektinhalte kindgerecht sind (z.B. keine Gewalt gegen Menschen oder Tiere, keine Pornografie).\nDie Arbeit mit sozialen Netzwerken wie Facebook oder Twitter ist erlaubt, damit die Kinder und Jugendlichen mit Hilfe der Mentoren den verantwortlichen Umgang damit erlernen. Voraussetzung ist aber, dass das Kind alt genug entsprechend der Nutzungsbedingungen der jeweiligen Plattform ist (z.B. bei Facebook muss das Kind mindestens 13 Jahre alt sein).\nWie funktionieren CoderDojos? Die Treffen finden in der Regel wöchentlich statt. Die Kinder und Jugendlichen treffen sich mit freiwilligen, technisch versierten Mentoren, um zusammen zu programmieren und unter Anleitung ihre Fähigkeiten zu entwickeln und auszubauen.\nDie Kinder und Jugendlichen sollen zum selbständigen Entdecken und Kreativsein angeregt werden. Die oberste Regel lautet, dass die Arbeit an den Projekten Spaß machen und cool sein muss.\nFür Anfänger haben wir einige spannende Projekte, die wir vorschlagen können. Wir richten uns aber ganz nach den Ideen und Vorschlägen der Kinder und Jugendlichen. Sie sollen die Möglichkeiten haben, all das am Computer auszuprobieren, das sie immer schon interessiert hat.\nWas kostet die Teilnahme? Nichts, kein Teilnahmegebühr, kein Abo, keine finanziellen Verpflichtungen!\nAlle Mentoren und Helfer, die bei den CoderDojos mitmachen, sind Freiwillige und bekommen für ihre Tätigkeiten kein Geld. Alle eventuellen Ausgaben für die Organisation und Durchführung der CoderDojos werden mit Hilfe von Spenden und Förderungen gedeckt.\nFalls Ihr Kind Projekte machen möchte, für die spezielle Hardware (z.B. Lego Mindstorms, TinkerForge) oder Software (z.B. Minecraft) notwendig sind und sollten Sie damit einverstanden sein, sind die Kosten für Hard- und Software von Ihnen zu tragen. Parallel dazu werden wir versuchen, kleinere Anschaffungen als Grundlage für interessante Projekte mit Hilfe von Sponsoren abzuwickeln, damit Ihnen möglichst wenig Kosten entstehen.\nGrundsätzlich ist es aber nicht notwendig Hard- oder Software für Ihr Kind zu kaufen. Wir werden dafür sorgen, dass in unserem Programm immer kostenfreie Alternativen angeboten werden.\nIst das CoderDojo das Richtige für mein Kind? Voraussetzung für die Teilnahme an unseren CoderDojos ist, dass das Kind zwischen 8 und 17 Jahren alt ist. Vorkenntnisse sind nicht notwendig.\nEs ist natürlich einfacher, wenn Ihr Kind schon einmal einen Computer bedient hat. Wenn nicht, können wir das aber rasch nachholen. Es ist ausdrücklich nicht Voraussetzung, dass Ihr Kind schon programmieren kann. Gerade das soll es ja im CoderDojo lernen.\nEs ist schwer im Vorhinein herauszufinden, ob ein Kind Spaß beim CoderDojo haben wird. Am einfachsten ist es, einfach vorbeizuschauen und es auszuprobieren. Wenn es Spaß macht, freuen wir uns über eine regelmäßige Teilnahme.\nMein Kind kann schon programmieren, darf es trotzdem kommen? Natürlich! Falls Ihr Kind schon Grundlagen der Softwareentwicklung beherrscht, begleiten die Mentoren es bei den Schritten zu komplexeren Projekten.\nAußerdem sollen Kinder und Jugendliche im CoderDojo gemeinsam Dinge ausprobieren. Erfahrenere Teilnehmer können jüngeren behilflich sein und so soziale Kompetenzen erlernen, die über das Programmieren hinaus gehen.\nWas muss ich als Elternteil beachten? Falls Ihr Kind jünger als 13 Jahre ist, muss es von einem Erwachsenen zum CoderDojo begleitet werden, der während des gesamten CoderDojos anwesend ist.\nBegleitpersonen sind natürlich herzlich eingeladen, als Mentoren oder anderweitige Helfer mitzuwirken. Bei einem CoderDojo gibt es auch viele Dinge abseits von Programmieren, die zu tun sind. Je mehr helfende Hände da sind, desto mehr können sich die Mentoren auf die Arbeit mit den Kindern und Jugendlichen konzentrieren.\nBeim Löten im Speziellen ist es von Vorteil, wenn die Begleitpersonen die Kinder unterstützen und darauf achten, dass sie mit dem Werkzeug richtig umgehen. Darüber hinaus haben die Kinder eventuell mehr Spaß daran, wenn mit den Eltern gemeinsam ein Projekt umgesetzt wird.\nAls Programmierclub möchten wir natürlich auch moderne Wege zur Kommunikation mit Teilnehmern, Eltern, Mentoren und Medien nutzen (z.B. Blogs, Facebook, Twitter). Sollten Sie keine Fotos Ihres Kindes wünschen, bitten wir Sie um einen entsprechenden Hinweis persönlich beim CoderDojo oder per Email (Kontaktinformationen).\nWann kann man einsteigen? Jederzeit.\nEs sind immer mehrere Mentoren anwesend, so können wir sowohl auf Anfänger als auch auf Fortgeschrittene eingehen. Für den ersten Besuch ist eine Anmeldung notwendig. Nach Erhalt eines Mitgliedsausweis ist keine Anmeldung mehr nötig.\nBraucht mein Kind einen Laptop? Grundsätzlich schon. Der Laptop muss aber nicht besonders schnell sein. Es ist egal, ob er mit Windows, Mac OS oder Linux betrieben wird. iPads, Android-Tablets oder Smartphones reichen nicht aus.\nFalls ein Kind teilnehmen möchte, das keinen eigenen Laptop mitbringen kann, nehmen Sie bitte mit uns Kontakt auf. Wir haben eine limitierte Anzahl an Geräten, die wir während der CoderDojos zur Verfügung stellen können.\nNeugierig geworden? Falls ja, melden Sie Ihr Kind zum ersten Besuch beim CoderDojo Linz an und kommen Sie bei uns vorbei.\n","permalink":"https://digital-austria.at/infos/eltern/","summary":"Informationen für Eltern Was ist ein CoderDojo? In der weltweiten CoderDojo Gemeinschaft bieten Freiwillige Programmierclubs für Kinder und Jugendliche an. Dort wird spielerisch Technologie entdeckt und gelernt wie man Code schreibt, Webseiten entwickelt, Apps und Spiele programmiert und vieles mehr. Technologieinteressierte Kinder treffen Gleichgesinnte und können sich über ihre Projekte austauschen.\nGemeinsames Entdecken, Teamarbeit, Mentoring sowie selbstorganisiertes Lernen und Experimentieren stehen im CoderDojo im Vordergrund. Offenheit, gegenseitiges Helfen und das Weitergeben von erworbenem Wissen sind wichtige Grundprinzipien.","title":"Informationen für Eltern"},{"content":"Neugierig auf Technik und Programmieren? Wolltest du immer schon wissen, wie Computer, iPad oder Smartphone funktionieren? Möchtest du Computerspiele nicht nur spielen sondern selbst programmieren? Reicht es dir nicht, deinen Status auf Facebook zu posten? Du möchtest lieber deine ganz eigene Webseite?\nDann bist du richtig beim CoderDojo!\nWas sind CoderDojos? In Japan trifft man sich in einem Dojo, um Kampfsportarten wie Judo oder Karate zu üben. Beim CoderDojo treffen wir uns, um zu \u0026ldquo;coden\u0026rdquo;, also zu programmieren.\nDie oberste Regel im CoderDojo lautet: Unsere Projekte sind cool! Das CoderDojo ist keine Schule oder Nachhilfestunde. Junge Hacker und solche, die es werden wollen, treffen sich, um gemeinsam an spannenden Projekten zu arbeiten.\nIm CoderDojo habt ihr Hilfe von erwachsenen Mentoren, die viel technische Erfahrung und technisches Wissen haben. Sie begleiten euch bei den ersten Schritten. Sie liefern Ideen für eure ersten Programme. Sie sind für euch da, wenn Ihr schon erfahrener seid und eigene Projekte umsetzen möchtet.\nWie läuft ein CoderDojo ab? Ihr kommt vorbei, wenn ihr Lust und Zeit habt.\n**Wiener Dojos finden in der Regel alle zwei wöchentlich statt. Tullner Dojos üblicherweise am letzten Freitag im Monat. **\nWenn ihr regelmäßig kommt, freut uns das besonders. Es gibt aber keine Verpflichtung, bei jedem Termin dabeizusein. Für den ersten Besuch ist eine Anmeldung notwendig. Nach Erhalt eines Mitgliedsausweis ist keine Anmeldung mehr nötig. Ihr kommt wenn ihr Zeit und Lust habt.\nBitte schaut mit euren Eltern die Informationen für Eltern aufmerksam durch. Falls Ihr jünger als 13 Jahre alt seid, muss eine erwachsene Begleitperson mit euch zum CoderDojo kommen und die ganze Zeit anwesend bleiben.\nWas wird beim CoderDojo gemacht? Eure Ideen stehen im Mittelpunkt Grundsätzlich gilt: eure Ideen stehen im Mittelpunkt. Wenn ihr eine Idee für ein cooles Programmier- oder Elektronikprojekt habt, bringt sie mit.\nFalls ihr erst am Anfang steht oder neue Technologien kennenlernen möchtet, machen euch die Mentoren Vorschläge für erste Schritte. Hier einige Beispiele:\nFür Anfänger: Scratch Wenn du noch nie programmiert hast, lernst du als erstes Scratch kennen. Man lernt damit die Grundlagen von Programmierung auf ganz einfache, grafische Art. Du kannst deine Projekte mit anderen teilen oder auf Projekten anderer aufbauen.\nScratch ist aber nicht nur auf einfache Programme beschränkt. Wenn ihr mehr Erfahrung habt, könnt ihr sogar Spiele entwickeln und diese im Internet eurer Familie oder euren Freunden zum Ausprobieren geben.\nFür Bastler: Micro:bit Egal ob du schon programmiert hast oder nicht, beim Micro:bit bist du als gut aufgehoben, wenn du die Dinge gerne in die Hand nimmst. Du lernst damit die Grundlagen von Programmierung ebenfalls auf ganz einfache, grafische Art oder alternativ hier auch in JavaScript oder Python. Du kannst deine Projekte mit anderen teilen oder auf Projekten anderer aufbauen.\nDen Micro:bit kannst du dabei, wenn du bastlersich und elektronisches begabt bist, auch für eigene Schaltungen verwenden.\nFür Internet-Entdecker Wenn ihr ein wenig erfahrener und neugierig auf die Welt des Internets seid, dann helfen wir euch, eure eigene Webseite zu bauen. Ob eigener Blog, Fotosammlung, Browser-Spiele oder - wenn ihr schon alt genug seid - Facebook-App, euren Ideen sind keine Grenzen gesetzt.\nEure Mentoren helfen euch, HTML, CSS und JavaScript zu erkunden. Wir haben einige echte Vollprofis im Team, von denen ihr viel lernen könnt.\nFür Fortgeschrittene Im CoderDojo könnt ihr natürlich auch professionelle Programmiersprachen wie Python, C#, Java oder C++ lernen. Das ist natürlich erst etwas für die Erfahreneren unter euch. Solche Programmiersprachen öffnen eine ganz neue Welt für euch. Minecraft Mods, Elektronikprojekte mit Raspberry Pi und vieles mehr warten dann auf euch.\nThementage Wir bemühen uns, immer wieder Gäste einzuladen, die besonders spannende Themen im Rahmen von Thementagen vorstellen. Das bringt euch sicher auf spannende Ideen für zukünftige Projekte.\nDie Regeln im CoderDojo Jede Gemeinschaft braucht ein paar Regeln, damit sie funktioniert. Hier sind unsere CoderDojo Regeln:\nWir machen coole Projekte, die Spaß machen. Als Team helfen wir uns gegenseitig, wenn jemand Hilfe beim Lösen eines kniffligen Problems braucht. Das CoderDojo ist kein Treffpunkt zum Computerspielen. Wenn wir Lust auf Computerspiele haben, bauen wir sie uns selbst. Es gibt keine dummen Fragen. Etwas nicht zu wissen, ist keine Schande. Es sind auch jüngere Kinder beim CoderDojo und deshalb müssen alle Projektinhalte auch für sie geeignet sein. Wir halten uns an Gesetze und Regeln. Computerkriminalität jeder Art ist tabu. Wir gehen sorgfältig mit unseren Geräten um. Wir teilen unsere Arbeitsergebnisse, damit andere davon lernen oder darauf aufbauen können. Neugierig geworden? Na dann, sprich mit deinen Eltern, ob sie einverstanden sind. Falls ja, melde dich gleich zu deinem erste Besuch beim CoderDojo Tulln oder Wien an und schau bei uns vorbei.\nWir freuen uns auf dich!\n","permalink":"https://digital-austria.at/infos/kinder-und-jugendliche/","summary":"Neugierig auf Technik und Programmieren? Wolltest du immer schon wissen, wie Computer, iPad oder Smartphone funktionieren? Möchtest du Computerspiele nicht nur spielen sondern selbst programmieren? Reicht es dir nicht, deinen Status auf Facebook zu posten? Du möchtest lieber deine ganz eigene Webseite?\nDann bist du richtig beim CoderDojo!\nWas sind CoderDojos? In Japan trifft man sich in einem Dojo, um Kampfsportarten wie Judo oder Karate zu üben. Beim CoderDojo treffen wir uns, um zu \u0026ldquo;coden\u0026rdquo;, also zu programmieren.","title":"Informationen für Kinder und Jugendliche"},{"content":"Wir suchen Mentoren! Du kannst gut programmieren oder bist ein Elektronik-Crack? Dann brauchen wir dich als Mentor.\nAls Mentoren begleiten wir in CoderDojos Kinder beim spielerischen Entdecken ihrer Begeisterung für Technik und Softwareentwicklung. Unsere Aufgaben sind:\nVermitteln der Grundlagen für Anfänger. Den Kindern helfen, falls sie an Grenzen stoßen. \u0026ldquo;Coole\u0026rdquo; Projektideen vorschlagen, falls die Kinder einmal keine eigenen Ideen mitbringen. Mithelfen bei der Entwicklung von Lern- und Übungsunterlagen (z.B. Dojo Sushi Cards). Und das wichtigste: Kinder für Technik und Programmieren begeistern. Häufige Fragen Ist das eine dauerhafte Verpflichtung? Nein, auch punktuelles Mitmachen ist möglich.\nNatürlich freuen wir uns, wenn Mentoren regelmäßig kommen. Das hilft sowohl bei der Planung der CoderDojos als auch in der Beziehung zu den Kindern und Jugendlichen, die besonders interessiert sind und daher regelmäßig kommen.\nDu bist aber auch willkommen, wenn du nur hin und wieder Zeit hast. Neben den laufenden Themen wie Scratch, Micro:bit oder Grundlagen der Web-Entwicklung organisieren wir auch spezielle Thementage, bei denen Gastmentoren ein spezielles Thema (z.B. etwas in Richtung Elektronik) vorstellen und Beispielprojekte vorschlagen.\nWann sind die CoderDojos? In der Regel Freitag am Nachmittag.\nIn Wien in der Regel jede zweite Woche und in Tulln meistens am letzten Freitag des Monats.\nWoher weiß ich, ob ich als Mentor geeignet bin? Wenn du technikbegeistert bist und dein Wissen gerne weitergibst, solltest du es probieren!\nEs ist schwer vorherzusagen, ob dir die Arbeit mit den Kindern und Jugendlichen Spaß macht. Du kannst ohne weiteres einmal vorbeikommen und in ein CoderDojo hineinschnuppern.\nBin ich alleine für kleine Kinder verantwortlich? Nein. Kinder, die jünger als 13 Jahre sind, müssen von einer erwachsenen Begleitperson begleitet werden und diese muss während der Veranstaltung anwesend bleiben.\nCoderDojo Mentoren haben keine Erziehungsaufgabe, es geht auch nicht um ein Betreuungsangebot, das Eltern zeitlich entlasten soll. Mentoren sollen Kinder und Jugendliche beim Entdecken von Technik und beim Lernen des Programmierens begleiten.\nWie viel Zeit muss ich einplanen? Das hängt stark von dir selbst ab.\nZumindest die Zeit für das CoderDojo selbst. Wir brauchen aber auch Mentoren, die darüber hinaus Zeit für vorbereitende Arbeiten investieren können und wollen.\nWie gehe ich das an? Nimm bitte einfach mit uns Kontakt auf.\nWir tauschen dann unsere Kontaktdaten aus und besprechen, wie und wann du als Mentor einsteigen kannst.\u0026lt;\u0026gt;\n","permalink":"https://digital-austria.at/infos/mentoren/","summary":"Wir suchen Mentoren! Du kannst gut programmieren oder bist ein Elektronik-Crack? Dann brauchen wir dich als Mentor.\nAls Mentoren begleiten wir in CoderDojos Kinder beim spielerischen Entdecken ihrer Begeisterung für Technik und Softwareentwicklung. Unsere Aufgaben sind:\nVermitteln der Grundlagen für Anfänger. Den Kindern helfen, falls sie an Grenzen stoßen. \u0026ldquo;Coole\u0026rdquo; Projektideen vorschlagen, falls die Kinder einmal keine eigenen Ideen mitbringen. Mithelfen bei der Entwicklung von Lern- und Übungsunterlagen (z.B. Dojo Sushi Cards).","title":"Informationen für Mentoren"},{"content":"CoderDojo an Schulen Einleitung Um möglichst vielen Kindern den Einstieg in das Programmieren zu ermöglichen, bieten wir Gast-CoderDojos an Schulen an.\nCoderDojo ist ein von ehrenamtlichen Mentorinnen und Mentoren getragener Programmierclubs. Alle Personen in unserem Mentoringteam sind berufstätig. Sie investieren ihre Freizeit, um im CoderDojo mitzuhelfen. Aus diesem Grund bitten wir um Verständnis, dass wir nicht alle Einladungen an Schulen annehmen können. Bitte verstehen Sie das nicht als mangelndes Interesse, ganz im Gegenteil. Wir bemühen uns, so vielen Anfragen wie möglich nachzukommen. Manchmal fehlt es uns aber an Ressourcen.\nHäufige Fragen Wie tritt man mit uns wegen Gast-CoderDojo in Kontakt? Am besten per Email (siehe hallo@digital-austria.at).\nWas kostet ein Gast-CoderDojo? Gast-CoderDojos sind sowohl für die Schule als auch für die Kinder kostenlos.\nFalls aus dem Gast-CoderDojo eine regelmäßig stattfindende Aktivität wird (z.B. außerschulische Aktivität am Nachmittag) wird zwischen Schule und uns ein Unkostenbeitrag pro Schülerin und Schüler vereinbart.\nWie wird ausgewählt? Wir bekommen üblicherweise mehr Einladungen als wir umsetzen können. Bei der Auswahl der Schulen geht es uns primär darum, ob die Schule ein Konzept hat, wie aus unserem Gastauftritt ein regelmäßiges Einbauen von Programmieren in den Unterricht wird. Insofern sind folgende Kriterien besonders wichtig:\nHelfen Lehrerinnen und Lehrer beim Gast-CoderDojo mit und sammeln dabei Erfahrung, wie Kinder und Jugendliche für Programmieren begeistert werden können? Gibt es einen Plan, wie die Schule Programmieren längerfristig im Unterricht oder als außerschulische Aktivität etablieren möchte? Was bieten wir inhaltlich an? Bei Gast-CoderDojos kann grundsätzlich alles gemacht werden, was wir auch im normalen CoderDojo machen. Beispiele:\nFür Kinder: Einstieg ins Programmieren mit Scratch Für Kinder und Jugendliche: Einstieg in Elektronik mit Micro:bit Was muss die Schule bereitstellen? Strom für die Laptops Idealerweise WLAN mit Internetzugang (wir haben zur Not auch mobiles Internet) Nach Vereinbarung des Inhalts stellen wir Angaben für Übungsbeispiele zur Verfügung, die von der Schule entsprechend der Anzahl an teilnehmenden Personen ausgedruckt werden müssen Kinder und Jugendliche können natürlich eigene Laptops im CoderDojo verwenden Bei einer größeren Anzahl an Kindern und Jugendlichen ist ein Beamer hilfreich, über den erste Schritte gezeigt werden können Welche Tage und Uhrzeiten sind möglich? Da unsere Mentorinnen und Mentoren berufstätig sind, bevorzugen wir Termine am späteren Nachmittag. Freitag Nachmittag ist beispielsweise ein guter Termin (sofern an dem jeweiligen Tag kein CoderDojo ist.\nFotos Da wir uns über Spenden finanzieren, müssen wir über unsere Aktivitäten berichten. Das machen wir primär über soziale Medien. Insofern machen wir oft Fotos von Veranstaltungen und veröffentliche diese. Die Schule muss sicherstellen, dass das in Ordnung ist. Falls keine Fotos gemacht werden dürfen, muss uns das vorab mitgeteilt werden.\nWir veröffentlichen keine Fotos von Kindern und Jugendlichen in Verbindung mit ihren Namen.\n","permalink":"https://digital-austria.at/infos/schulen/","summary":"CoderDojo an Schulen Einleitung Um möglichst vielen Kindern den Einstieg in das Programmieren zu ermöglichen, bieten wir Gast-CoderDojos an Schulen an.\nCoderDojo ist ein von ehrenamtlichen Mentorinnen und Mentoren getragener Programmierclubs. Alle Personen in unserem Mentoringteam sind berufstätig. Sie investieren ihre Freizeit, um im CoderDojo mitzuhelfen. Aus diesem Grund bitten wir um Verständnis, dass wir nicht alle Einladungen an Schulen annehmen können. Bitte verstehen Sie das nicht als mangelndes Interesse, ganz im Gegenteil.","title":"Informationen für Schulen"},{"content":"Endlich können wir im März 2023 auch das CoderDojo Tulln starten! Eine Übersicht sowie auch eine Anmeldemöglichkeit unserer nächsten Dojos findest du bei Eventbrite.\nMicro:bit beim DojoTeilnehmer des Dojo probieren ihre mit einem Micro:bit entwickelten Spiele aus\nNach unserem Auftakt mit einem Dojo am 24. März planen wir monatliche weitere Dojos, jeweils am vorletzten oder letzten Freitag des Monats.\nDie Dojos können wir in den Räumlichkeiten der HAK Tulln durchführen.\nPS: Wir möchten auch darauf hinweisen, dass wir und alle Teilnehmer sich im Sinne eines gemeinschaftlichen und guten Miteainders an die Hausordnung unseres Gastgebers halten.\n","permalink":"https://digital-austria.at/dojos/tulln/","summary":"Endlich können wir im März 2023 auch das CoderDojo Tulln starten! Eine Übersicht sowie auch eine Anmeldemöglichkeit unserer nächsten Dojos findest du bei Eventbrite.\nMicro:bit beim DojoTeilnehmer des Dojo probieren ihre mit einem Micro:bit entwickelten Spiele aus\nNach unserem Auftakt mit einem Dojo am 24. März planen wir monatliche weitere Dojos, jeweils am vorletzten oder letzten Freitag des Monats.\nDie Dojos können wir in den Räumlichkeiten der HAK Tulln durchführen.","title":"CoderDojo Tulln"},{"content":" Die Stadt Wien unternimmt besondere Anstrengungen, um den Wiener Arbeitnehmerinnen beim Weiterkommen im Beruf zu helfen. Das Instrument dafür ist der waff. Wir richten unsere Unterstützungsleistungen punktgenau auf die Bedürfnisse der Arbeitnehmerinnen in Wien aus und entwickeln sie innovativ und flexibel weiter.\n(waff.at)\nAls Kooperationspartner des WAFF veranstaltet CoderDojo Wien regelmäßig Dojos im Rahmen der Wiener Wochen für Beruf und Weiterbildung des WAFF.\n","permalink":"https://digital-austria.at/projects/waff/","summary":"Die Stadt Wien unternimmt besondere Anstrengungen, um den Wiener Arbeitnehmerinnen beim Weiterkommen im Beruf zu helfen. Das Instrument dafür ist der waff. Wir richten unsere Unterstützungsleistungen punktgenau auf die Bedürfnisse der Arbeitnehmerinnen in Wien aus und entwickeln sie innovativ und flexibel weiter.\n(waff.at)\nAls Kooperationspartner des WAFF veranstaltet CoderDojo Wien regelmäßig Dojos im Rahmen der Wiener Wochen für Beruf und Weiterbildung des WAFF.","title":"WAFF"},{"content":"Hier geht\u0026rsquo;s zur Website von CoderDojo Wien.\nEine Übersicht sowie auch eine Anmeldemöglichkeit unserer nächsten Dojos findest du bei Eventbrite.\nDojo bei VerbundTeilnehmer programmieren bei unserem Dojo an ihrem Projekten\nDie Dojos können wir in den Räumlichkeiten unseres Kooperationspartners Verbund durchführen.\n","permalink":"https://digital-austria.at/dojos/wien/","summary":"Hier geht\u0026rsquo;s zur Website von CoderDojo Wien.\nEine Übersicht sowie auch eine Anmeldemöglichkeit unserer nächsten Dojos findest du bei Eventbrite.\nDojo bei VerbundTeilnehmer programmieren bei unserem Dojo an ihrem Projekten\nDie Dojos können wir in den Räumlichkeiten unseres Kooperationspartners Verbund durchführen.","title":"CoderDojo Wien"},{"content":"Wer sind wir? digital.austria ist ein gemeinnütziger Verein der in ganz Österreich tätig ist, an dessen oberster Stelle Teamarbeit und Mentoring zur Vermittlung von Informationstechnologie und Programmierung an Kinder steht.\nUnsere Vision ist es, jedem Kind einem Raum zu bieten, in welchem es seine Ideen verwirklichen kann. Deswegen haben wir uns entschlossen den Kindern und Jugendlichen die Möglichkeit zu geben sich in einem sozialen Umfeld auf eine informelle, kreative Art und Weise weiterbilden zu können. Ein Raum in dem die Erforschung von Technologie Freude macht. Doch damit das möglich ist, benötigen sie vielerorts unsere Unterstützung.\nWieso Sponsoring? Unsere Mentoren engagieren sich ehrenamtlich in ihren Freizeit bei Vorbereitung der Programmierbeispiele sowie bei der Betreuung während der CoderDojos. Um möglichst viele Kinder zu erreichen, sollen für die Besucher keinerlei Gebühren oder sonstige finanzielle Verpflichtungen anfallen. Daher wird kein Eintrittspreis, Mitgliedschaft oder sonstiges für die Teilnahme der Kinder verlangt.\nUnsere Mitgründer und Mentoren spenden viel Zeit, Engagement und ihre eigenen Mittel um dieses einmalige Projekt in Österreich fortführen zu können. Hilf mit.\nWelchen Beitrag kann ich leisten? Egal ob mittels Mithilfe als Mentor oder helfende Hand bei den Veranstaltungen, Spende von Sachmitteln/Lizenzen oder durch finanzielle Unterstützung, wir freuen uns über jeden Beitrag.\nGeldspenden Im Folgenden findest du Vorschläge, wie du uns finanziell unterstützen kannst. Deiner Kreativität sind natürlich keine Grenzen gesetzt, wir freuen uns über neue Vorschläge. Die Preise sind Richtwerte.\nEinmaliger Betrag Das Geld wird ausschließlich für die Kinder verwendet, z.B. für das Ausdrucken der Anleitungen, für Obst während der Veranstaltungen, oder für die Veranstaltung eines CoderDojo Festes für die Kinder.\nWenn gewünscht, wirst du gerne auf unserer Webseite namentlich erwähnt. Schicke uns dazu bitte eine kurze Info an hallo@digital-austria.at.\nBankverbindung Erste Bank\nIBAN: AT68 2011 1846 3821 0300\nBIC: GIBAATWWXXX\nPayPal Zeit- und Sachspenden Mentor Du bist technikbegeistert und gibst gern dein Wissen weiter? Dann unterstütze uns als Mentor. Entweder regelmäßig oder punktuell. Oder als Gast-Mentor an speziellen Thementagen. Alles was wir wollen ist dich und deine Zeit.\nDu bist interessiert oder hast noch Fragen, dann sieh dir unsere Informationen für Mentoren an oder schreib uns eine E-Mail an hallo@digital-austria.at.\nHelfende Hand Bei einem CoderDojo gibt es auch viele Dinge abseits von Programmieren, die zu tun sind. Sei es das Her- und Wegräumen der Bestuhlung, Her- und Wegräumen von Getränken und Obst, Registrierung der Kinder am Anfang jeder Veranstaltung, oder einfach nur als Ansprechperson da sein. Wir freuen uns auf deine Unterstützung durch deine Zeit.\nDu bist interessiert oder hast noch Fragen, dann schreib uns eine E-Mail an hallo@digital-austria.at\nSachmittelspende Du hast deinen funktionierenden Laptop gegen ein neues Gerät ausgetauscht? Wir sind immer auf der Suche nach funktionierenden Laptops, die wir den Kindern als Leihgeräte während der Veranstaltung zur Verfügung stellen können. Oder du verwendest deinen Raspberry Pi nicht mehr? Einfach vorbei bringen.\nVoraussetzung ist natürlich, dass die Geräte funktionieren.\nLizenzspende Du möchtest den Kindern die Möglichkeit geben, kommerzielle Werkzeuge zu verwenden? Dann freuen wir uns über die Spende von Lizenzen.\n","permalink":"https://digital-austria.at/page/sponsor/","summary":"Wer sind wir? digital.austria ist ein gemeinnütziger Verein der in ganz Österreich tätig ist, an dessen oberster Stelle Teamarbeit und Mentoring zur Vermittlung von Informationstechnologie und Programmierung an Kinder steht.\nUnsere Vision ist es, jedem Kind einem Raum zu bieten, in welchem es seine Ideen verwirklichen kann. Deswegen haben wir uns entschlossen den Kindern und Jugendlichen die Möglichkeit zu geben sich in einem sozialen Umfeld auf eine informelle, kreative Art und Weise weiterbilden zu können.","title":"Sponsoring"},{"content":"In Presse und Medien Profil, 24. April 2017: Kinderclub: Computerspiele selber programmieren\nVerbund, 26. Jänner 2018: CoderDojo: Nachwuchs-Programmierer bei VERBUND\nPressetext.at, 14. Februar 2018: Hackathon für CoderDojo-Mentoren\nPressetext.at, 15. Mai 2018: CoderDojo at WeAreDevelopers\nPressetext.at, 17. Oktober 2018: CoderDojo auf der EU Code Week 2018\nBVZ.at, 24. Jänner 2019: Programmier-Club für Kinder: „CoderDojo“ sucht Mentoren\nNÖN, 2. April 2023: CoderDojo jetzt auch in Tulln\nMeinBezirk.at, 13. Mai 2023: Programmier-Club CoderDojo zu Gast bei Dynatrace Profil, 27. Juni 2023: Die Sprache der Zukunft lernen\nConfare Blog, 17. August 2023: CoderDojo: Ein sicherer und sozialer Raum für Kinder, um Technologie zu erkunden\nAnfragen Wir stehen gerne für deine Anfrage zur Verfügung, bitte wende dich an unsere Obleute oder kontaktiere uns unter:\nhallo@digital-austria.at\n","permalink":"https://digital-austria.at/page/press/","summary":"In Presse und Medien Profil, 24. April 2017: Kinderclub: Computerspiele selber programmieren\nVerbund, 26. Jänner 2018: CoderDojo: Nachwuchs-Programmierer bei VERBUND\nPressetext.at, 14. Februar 2018: Hackathon für CoderDojo-Mentoren\nPressetext.at, 15. Mai 2018: CoderDojo at WeAreDevelopers\nPressetext.at, 17. Oktober 2018: CoderDojo auf der EU Code Week 2018\nBVZ.at, 24. Jänner 2019: Programmier-Club für Kinder: „CoderDojo“ sucht Mentoren\nNÖN, 2. April 2023: CoderDojo jetzt auch in Tulln\nMeinBezirk.at, 13. Mai 2023: Programmier-Club CoderDojo zu Gast bei Dynatrace Profil, 27.","title":"Medien und Presse"},{"content":"Medieninhaber und Herausgeber dieser Website digital.austria – Verein zur Förderung der Informationstechnologie Obmann: DI Mag. Daniel Wagner\nBahnweg 3 Haus 1 3425 Langenlebarn Austria\nE-Mail hallo@digital-austria.at\nRechtsform: Eintragener Verein Vereinssitz: Langenlebarn, Austria Vereinsregister Nummer: 1014456765 Vereinsstatuten: Vereinsstatuten Vereinsregisterauszug: Vereinsregisterauszug\nZuständige Behörde: Bezirkshauptmannschaft Tulln\nVereinszweck Der Verein, dessen Tätigkeit nicht auf Gewinn gerichtet ist, bezweckt die Förderung der Kenntnisse der Allgemeinheit über Informationstechnologie im Allgemeinen und Softwareentwicklung im Speziellen.\nDatenschutz Wir sammeln Nutzungsdaten mithilfe von Google Analytics, um den Website-Traffic zu visualisieren.\nAlle Daten werden anonymisiert und wir verkaufen oder teilen keine Daten mit Dritten.\nWenn Sie ablehnen, werden keinerlei Informationen gesammelt.\nHaftungsausschluss Die Informationen auf dieser Website wurden mit größtmöglicher Sorgfalt erstellt. Es können jedoch Fehler nicht vollständig ausgeschlossen werden. Wir übernehmen keine rechtliche Verantwortung oder Haftung für möglicherweise noch vorhandene ungenaue Informationen und deren Konsequenzen. Links, die auf dieser Website bereitgestellt werden, führen auch zu externen redaktionellen Angeboten. Diese Links werden als Service und nur zu Informationszwecken bereitgestellt; sie stellen keine Billigung oder Zustimmung von uns dar. Wir übernehmen keine Verantwortung für die Genauigkeit, Legalität oder den Inhalt der externen Website oder für den Inhalt von nachfolgenden Links. Wenden Sie sich an die externe Website, um Antworten auf Fragen zu ihrem Inhalt zu erhalten.\n","permalink":"https://digital-austria.at/page/imprint/","summary":"Medieninhaber und Herausgeber dieser Website digital.austria – Verein zur Förderung der Informationstechnologie Obmann: DI Mag. Daniel Wagner\nBahnweg 3 Haus 1 3425 Langenlebarn Austria\nE-Mail hallo@digital-austria.at\nRechtsform: Eintragener Verein Vereinssitz: Langenlebarn, Austria Vereinsregister Nummer: 1014456765 Vereinsstatuten: Vereinsstatuten Vereinsregisterauszug: Vereinsregisterauszug\nZuständige Behörde: Bezirkshauptmannschaft Tulln\nVereinszweck Der Verein, dessen Tätigkeit nicht auf Gewinn gerichtet ist, bezweckt die Förderung der Kenntnisse der Allgemeinheit über Informationstechnologie im Allgemeinen und Softwareentwicklung im Speziellen.\nDatenschutz Wir sammeln Nutzungsdaten mithilfe von Google Analytics, um den Website-Traffic zu visualisieren.","title":"Impressum \u0026 Offenlegung"},{"content":"Gemeinsam mit dem ebenfalls in Tulln ansässigen Verein Verein TechnologyKids veranstalten wir heuer am 15. Dezember 2023 im edu-Makerspace Tulln eine Coding Weihnachtswerkstatt. Lass dich überraschen.\nDie Teilnahme ist wie immer kostenfrei und die Anmeldung ist bereits über unsere Anmeldeseite möglich.\nWir freuen uns auf euren Besuch. ","permalink":"https://digital-austria.at/posts/2023-11-21-coding-weihnachtswerkstatt-tulln/","summary":"Gemeinsam mit dem ebenfalls in Tulln ansässigen Verein Verein TechnologyKids veranstalten wir heuer am 15. Dezember 2023 im edu-Makerspace Tulln eine Coding Weihnachtswerkstatt. Lass dich überraschen.\nDie Teilnahme ist wie immer kostenfrei und die Anmeldung ist bereits über unsere Anmeldeseite möglich.\nWir freuen uns auf euren Besuch. ","title":"Coding Weihnachtswerkstatt Tulln 2023"},{"content":"Engagement für die Gesellschaft, für die Umwelt, für Wien ist gelebte Teilhabe. Kinder und Jugendliche wollen mithelfen und mitgestalten – also unterstützen wir sie!\nDas Projekt Im Rahmen der Wiener Ehrenamtswoche starten wir heuer ein auch für uns völlig neues Format. Das CoderDojo Youth for Youth. Wir bringen Schüler_innen der Abteilung Informationstechnologie am TGM mit einer Klasse des BRG14 zusammen.\nUnsere Mentor_innen werden den freiwillig teilnehmenden Schüler_innen des TGM dabei helfen ihre ersten eigenen Erfahrungen als ehrenamtliche Mentor_innen zu sammeln. Sie helfen uns dabei einer Klasse des BRG14 einen ersten Einblick in die Welt des Software-Engineerings zu bekommen.\nInformation zur Anmeldung für interessierte Klassen sind online bei wienxtra unter https://www.wienxtra.at/schulevents/kontakt/event/33860/ verfügbar.\nFür Schulen, welche diesmal nicht dabei sein können, haben wir auch noch weitere Infos wie eine Zusammenarbeit mit CoderDojo funktionieren kann unter Infos für Schulen\nUnsere Kooperationspartner WIENXTRASchulevents\nBRG 14Linzer Straße\nTGMDie Schule der Technik\n","permalink":"https://digital-austria.at/projects/wiener-ehrenamtswoche-2023/","summary":"Engagement für die Gesellschaft, für die Umwelt, für Wien ist gelebte Teilhabe. Kinder und Jugendliche wollen mithelfen und mitgestalten – also unterstützen wir sie!\nDas Projekt Im Rahmen der Wiener Ehrenamtswoche starten wir heuer ein auch für uns völlig neues Format. Das CoderDojo Youth for Youth. Wir bringen Schüler_innen der Abteilung Informationstechnologie am TGM mit einer Klasse des BRG14 zusammen.\nUnsere Mentor_innen werden den freiwillig teilnehmenden Schüler_innen des TGM dabei helfen ihre ersten eigenen Erfahrungen als ehrenamtliche Mentor_innen zu sammeln.","title":"Wiener Ehrenamtswoche 2023"}]